Metadata-Version: 2.1
Name: zato-ext-bunch
Version: 1.3
Summary: A dot-accessible dictionary (a la JavaScript objects)
Home-page: http://github.com/dsc/bunch
Author: David Schoonover
Author-email: dsc@less.ly
License: MIT
Keywords: bunch,dict,mapping,container,collection
Classifier: Development Status :: 5 - Production/Stable
Classifier: Intended Audience :: Developers
Classifier: Operating System :: OS Independent
Classifier: Programming Language :: Python
Classifier: Topic :: Software Development
Classifier: Topic :: Software Development :: Libraries
Classifier: Topic :: Utilities
Classifier: License :: OSI Approved :: MIT License
License-File: LICENSE.txt
